README.md
operaciones.py
setup.cfg
setup.py
ejercicio13_efm.egg-info/PKG-INFO
ejercicio13_efm.egg-info/SOURCES.txt
ejercicio13_efm.egg-info/dependency_links.txt
ejercicio13_efm.egg-info/requires.txt
ejercicio13_efm.egg-info/top_level.txt