Metadata-Version: 2.4
Name: ejercicio13-efm
Version: 0.2a0
Summary: Libreria de mates
Author: Erika Fernández Moreno
Author-email: erika@edrakon.tech
License: MIT
Keywords: mates,suma,resta,multiplicacion,division
Classifier: Development Status :: 3 - Alpha
Classifier: Intended Audience :: Developers
Classifier: Topic :: Software Development :: Build Tools
Classifier: License :: OSI Approved :: MIT License
Classifier: Programming Language :: Python :: 3.14
Requires-Python: >=3.14
Requires-Dist: pytest
Dynamic: author
Dynamic: author-email
Dynamic: classifier
Dynamic: keywords
Dynamic: license
Dynamic: requires-dist
Dynamic: requires-python
Dynamic: summary
